gh_issues/__init__.py
gh_issues/_api.py
gh_issues/_github.py
gh_issues/_issue_parser.py
gh_issues/_repo.py
gh_issues-2024.10.2a4.dist-info/LICENSE
gh_issues-2024.10.2a4.dist-info/METADATA
gh_issues-2024.10.2a4.dist-info/WHEEL
gh_issues-2024.10.2a4.dist-info/top_level.txt
gh_issues-2024.10.2a4.dist-info/RECORD
