Metadata-Version: 2.1
Name: gh_issues
Version: 2024.10.2a4
License: MIT
Keywords: github,issues,markdown
Requires-Python: >=3.10
License-File: LICENSE
Requires-Dist: httpx
Requires-Dist: markdown-it-py
Provides-Extra: dev
Requires-Dist: nox; extra == "dev"
Requires-Dist: pytest; extra == "dev"
Requires-Dist: pytest-httpx; extra == "dev"
Requires-Dist: pip-tools; extra == "dev"
Requires-Dist: pytest-cov; extra == "dev"
Requires-Dist: pre-commit; extra == "dev"
